tole/__init__.py
tole/tole_cli.py
tole/tole_gui.py
tole_tool-2.0.0.dist-info/METADATA
tole_tool-2.0.0.dist-info/WHEEL
tole_tool-2.0.0.dist-info/entry_points.txt
tole_tool-2.0.0.dist-info/top_level.txt
tole_tool-2.0.0.dist-info/RECORD
