Metadata-Version: 2.4
Name: tole-tool
Version: 2.0.0
Summary: The simplest Python to EXE converter with GUI and auto-assets (Alpha).
Home-page: https://pypi.org/project/tole-tool/
Author: wetoq
Classifier: Programming Language :: Python :: 3
Classifier: License :: OSI Approved :: MIT License
Classifier: Operating System :: Microsoft :: Windows
Requires-Dist: pyinstaller
Dynamic: author
Dynamic: classifier
Dynamic: description
Dynamic: description-content-type
Dynamic: home-page
Dynamic: requires-dist
Dynamic: summary
